dlpml/__init__.py
dlpml/classification/__init__.py
dlpml/classification/logistic_regressor.py
dlpml/regression/__init__.py
dlpml/regression/linear_regressor.py
dlpml-0.1.0.dist-info/LICENSE
dlpml-0.1.0.dist-info/METADATA
dlpml-0.1.0.dist-info/WHEEL
dlpml-0.1.0.dist-info/RECORD
