Metadata-Version: 2.1
Name: dlpml
Version: 0.1.0
Summary: Minimalist Machine Learning library
Author: mossdet
Author-email: mossdet.detector@gmail.com
Requires-Python: >=3.12,<4.0
Classifier: Programming Language :: Python :: 3
Classifier: Programming Language :: Python :: 3.12
Requires-Dist: jupyter (>=1.1.1,<2.0.0)
Requires-Dist: lab (>=8.3,<9.0)
Requires-Dist: matplotlib (>=3.9.2,<4.0.0)
Requires-Dist: numpy (>=2.1.3,<3.0.0)
Requires-Dist: pandas (>=2.2.3,<3.0.0)
